Workbook

Sheet Painel
B1: DEIXA COMIGO — Unit Economics por pessoa cuidada
B2: Preencha somente as células AMARELAS (texto azul). O resto calcula sozinho.
B3: Legenda: azul = você preenche · preto = calculado · verde = vem de outra aba
B5: RESULTADO POR PESSOA CUIDADA / MÊS
B6: Receita por pessoa cuidada (líquida do mix de desconto) | C6: ='Premissas'!C9
B7: (-) Custo humano (cenário típico P50) | C7: =-'Custo da Missão'!C20
B8: (-) Custo de tecnologia e IA | C8: =-'Premissas'!C16*'Custo da Missão'!C18
B9: (=) Margem de contribuição | C9: =C6+C7+C8
B10: Margem de contribuição (%) | C10: =IF(C6=0,0,C9/C6)
B11: Margem-alvo (porta 9.4) | C11: ='Premissas'!C20
B12: VEREDITO | C12: =IF(C10>=C11,"✓ FECHA A CONTA","✗ NÃO FECHA")
B14: CENÁRIO DE CAUDA (P90 — a pessoa que usa muito)
B15: Margem de contribuição no P90 | C15: =C6-'Custo da Missão'!C21-'Premissas'!C16*'Custo da Missão'!C19
B16: Margem % no P90 | C16: =IF(C6=0,0,C15/C6)
B17: Alerta da cauda | C17: =IF(C15<0,"⚠ PREJUÍZO no P90","ok") | E17: Se der prejuízo no P90: apertar limites do beta, subir preço ou cobrar missão extra.
B19: OPERAÇÃO NA ESCALA ESCOLHIDA
B20: Nº de pessoas cuidadas (cenário) | C20: ='Premissas'!C22
B21: Receita mensal total | C21: =C20*C6
B22: Custo variável total (P50) | C22: =C20*(-C7-C8)
B23: (-) Custos fixos mensais | C23: =-'Custos Fixos'!C15
B24: (=) Resultado mensal | C24: =C21-C22+C23
B25: Margem líquida (%) | C25: =IF(C21=0,0,C24/C21)
B27: PONTO DE EQUILÍBRIO E CAPACIDADE
B28: Ponto de equilíbrio (nº de pessoas cuidadas) | C28: =IF(C9<=0,0,ROUNDUP('Custos Fixos'!C15/C9,0))
B29: Horas humanas totais/mês na escala | C29: =C20*'Custo da Missão'!C18*'Custo da Missão'!C16/60
B30: Operadores necessários (jornada da premissa) | C30: =IF('Premissas'!C21=0,0,ROUNDUP(C28/'Premissas'!C21,1))
B32: TETO DO SIMPLES NACIONAL (alerta societário)
B33: Receita anual da Deixa Comigo neste cenário | C33: =C21*12
B34: (+) Receita anual das outras empresas do sócio | C34: ='Premissas'!C25
B35: (=) Receita bruta GLOBAL | C35: =C33+C34
B36: Teto do Simples (LC 123) | C36: ='Premissas'!C26
B37: Situação | C37: =IF(C35>C36,"⚠ ESTOURA O TETO — Simples inviável","✓ dentro do teto")
B38: Nº máximo de pessoas cuidadas dentro do Simples | C38: =IF(C6=0,0,ROUNDDOWN((C36-C34)/(C6*12),0))

Sheet Premissas
B1: PREMISSAS — preencha as células amarelas
B2: Todo número de entrada do modelo mora aqui. Nenhuma outra aba tem valor digitado.
B4: PREÇO
B5: Modelo aprovado: cobrança POR PESSOA CUIDADA (31/07/2026)
B6: Preço mensal por pessoa cuidada | C6: 390 | E6: HIPÓTESE — não é Preço Canônico. Definido na Etapa 10.
B7: Desconto na 2ª pessoa do mesmo núcleo | C7: 0.5 | E7: Espelha o custo marginal menor: 'o contato não dobra'.
B8: % de núcleos com 2 pessoas cuidadas | C8: 0.2 | E8: Estimativa; medir no piloto.
B9: Receita média efetiva por pessoa | C9: =C6*(1-C8*C7/2) | E9: Ajusta o preço cheio pelo mix de segundas pessoas com desconto.
B11: CUSTOS VARIÁVEIS
B12: Custo/hora carregado da operação humana | C12: 79.55 | E12: Fundador 31/07: SDR bom = R$ 6.000/mês. CLT c/ encargos (x1,75) = R$ 10.500 / 132h = R$ 79,55. Se PJ: use 47,73.
B13: [ref] Salário mensal do operador | C13: 6000 | E13: Fonte: fundador, 31/07/2026 — SDR de atendimento passivo.
B14: [ref] Multiplicador de encargos | C14: 1.75 | E14: CLT ~1,75 · PJ ~1,05. Célula de referência: recalcule a linha 12 se mudar.
B15: Custo/hora de especialista (escalonamento) | C15: 120 | E15: Casos que sobem para profissional habilitado.
B16: Custo de IA/software por missão | C16: 3 | E16: Tokens, telefonia, integrações.
B17: % das missões que escalam para especialista | C17: 0.1 | E17: Medir no piloto.
B19: METAS E CENÁRIO
B20: Margem-alvo mínima (porta 9.4) | C20: 0.3 | E20: Trava do motor: abaixo disso a conta não fecha.
B21: Horas produtivas por operador/mês | C21: 132 | E21: Ex.: 176h contratuais × 75% de produtividade.
B22: Nº de pessoas cuidadas no cenário | C22: 300 | E22: Objetivo da Etapa 6: 300 até jul/2027.
B24: CONTEXTO SOCIETÁRIO (para o alerta do Simples)
B25: Receita anual das outras empresas do sócio | C25: 4200000 | E25: Setfree: R$ 350k/mês x 12. Fonte: fundador, 31/07/2026.
B26: Teto da receita bruta global — Simples | C26: 4800000 | E26: LC 123/2006. Confirmar vigência com a Cony Services.

Sheet Custo da Missão
B1: CUSTO DA MISSÃO — o coração do modelo
B2: Catálogo do Produto Zero. Preencha os minutos humanos e a frequência de cada missão.
B4: Missão (catálogo) | C4: Minutos humanos | D4: Missões/mês (P50) | E4: Missões/mês (P90)
B5: Agenda e acesso (marcar, remarcar, confirmar) | C5: 25 | D5: 1 | E5: 2.5
B6: Documento claro (organizar e resumir) | C6: 30 | D6: 0.5 | E6: 1.5
B7: Três opções prontas (comparar prestadores) | C7: 45 | D7: 0.3 | E7: 1
B8: Protocolo acompanhado (convênio, ouvidoria) | C8: 60 | D8: 0.5 | E8: 2
B9: Plano de próximos passos | C9: 20 | D9: 0.3 | E9: 1
B10: Família alinhada (atualização factual) | C10: 15 | D10: 0.4 | E10: 1
B11: TOTAL | D11: =SUM(D5:D10) | E11: =SUM(E5:E10)
B13: CÁLCULO DO CUSTO POR PESSOA CUIDADA / MÊS
B16: Minutos humanos médios por missão | C16: =IF(C11=0,0,SUMPRODUCT(C5:C10,D5:D10)/D11) | F16: Média ponderada pela frequência real, não média simples.
B17: Custo humano por missão | C17: =C16/60*'Premissas'!C12+C16/60*'Premissas'!C17*('Premissas'!C15-'Premissas'!C12) | F17: Operador + parcela que escala para especialista.
B18: Missões por pessoa/mês (P50) | C18: =D11 | F18: Cenário típico.
B19: Missões por pessoa/mês (P90) | C19: =E11 | F19: A cauda: quem usa muito. É esta que decide o preço.
B20: CUSTO HUMANO por pessoa/mês (P50) | C20: =C17*C18 | F20: Vai para o Painel.
B21: CUSTO HUMANO por pessoa/mês (P90) | C21: =C17*C19 | F21: Vai para o alerta de cauda.
B23: ⚠ Enquanto o piloto não medir minutos reais por missão, todos estes números são estimativa. A porta 24.x deve cronometrar desde o primeiro cliente.

Sheet Custos Fixos
B1: CUSTOS FIXOS MENSAIS
B2: O que a empresa gasta independentemente de quantos clientes tem.
B5: Coordenação / gestão da operação | C5: 8000 | E5: Quem supervisiona a célula terceirizada.
B6: Tecnologia base (WhatsApp API, hospedagem, banco) | C6: 1500
B7: Ferramentas e assinaturas | C7: 800 | E7: IA, CRM, produtividade.
B8: Jurídico e contábil | C8: 2500 | E8: Contrato, LGPD, contabilidade mensal.
B9: Marketing e aquisição | C9: 5000 | E9: Ajustar conforme a Etapa 28.
B10: Estrutura (endereço fiscal, banco, taxas) | C10: 700
B11: Outros / reserva | C11: 1500
B15: TOTAL DE CUSTOS FIXOS / MÊS | C15: =SUM(C5:C11)
B17: Runway (porta 9.5)
B18: Caixa disponível hoje | C18: 0 | E18: ⚠ Preencher — a porta 9.5 exige caixa para ≥ 6 meses.
B19: Meses de runway sem receita | C19: =IF(C15=0,0,C18/C15)
B20: Situação da porta 9.5 | C20: =IF(C19>=6,"✓ ok (≥6 meses)","⚠ abaixo de 6 meses")

Sheet Como usar
B1: COMO USAR ESTA PLANILHA
B4: 1. Preencha as células AMARELAS da aba Premissas.
B5: O número mais importante — e o único que você ainda não tem — é o custo/hora carregado da operação (linha 12). Peça ao fornecedor: 'quanto custa uma hora produtiva de um operador, com encargos e gestão inclusos?'
B6: 2. Ajuste os minutos por missão na aba Custo da Missão.
B7: Os valores atuais são estimativa de partida. Use seu conhecimento do mercado para corrigir — e substitua por medição real assim que o piloto começar.
B8: 3. Revise os Custos Fixos.
B9: Inclua o que já sabe. E preencha o caixa disponível (linha 18) — a porta 9.5 do motor exige runway de 6 meses.
B10: 4. Leia o Painel.
B11: Ele responde as perguntas que travam a Etapa 9: a conta fecha? qual a margem? quantas pessoas para empatar? quantos operadores preciso? e o alerta do Simples.
B13: As três perguntas que esta planilha existe para responder:
B14: • A conta fecha no cenário típico (P50)?
B15: Painel, linha 12.
... B22: enquanto o piloto não medir minutos humanos reais por missão, tudo aqui é hipótese organizada — útil para decidir direção, insuficiente para fixar preço.
